numpy2ad/__init__.py
numpy2ad/ast_traversal.py
numpy2ad/base_transformer.py
numpy2ad/derivatives.py
numpy2ad/expr_transformer.py
numpy2ad/func_transformer.py
numpy2ad-0.1.1.dist-info/LICENSE.txt
numpy2ad-0.1.1.dist-info/METADATA
numpy2ad-0.1.1.dist-info/WHEEL
numpy2ad-0.1.1.dist-info/top_level.txt
numpy2ad-0.1.1.dist-info/RECORD
