Metadata-Version: 2.1
Name: numpy2ad
Version: 0.1.1
Summary: A Python package for automatic differentiation of Numpy matrix expressions by source transformation.
Author: Nicholas Book
Author-email: nicholasbook@googlemail.com
License: MIT
Classifier: Programming Language :: Python :: 3
Classifier: License :: OSI Approved :: MIT License
Requires-Python: >=3.10
License-File: LICENSE.txt
Requires-Dist: graphviz
